{
  "projectApplicationId": 453,
  "requirementId": 943,
  "files": [
    "frontend/src/views/view.ts"
  ],
  "activityMeta": [
    {
      "file": "frontend/src/views/view.ts",
      "requirementId": 943,
      "requirementName": "Build customer portal UI",
      "changes": 2,
      "modifiedRanges": [
        {
          "startLine": 1,
          "endLine": 3,
          "lineCount": 3
        }
      ],
      "timestamps": {
        "firstModified": "2026-07-12T06:11:13.523Z",
        "lastModified": "2026-07-12T06:11:29.665Z"
      },
      "activity": {
        "activeDurationSec": 16,
        "idleBreaks": 0,
        "avgIntervalSec": 8
      },
      "diffStats": {
        "linesAdded": 3,
        "linesDeleted": 0,
        "largeChangeEvents": 0
      },
      "patterns": {
        "burstEdits": false,
        "longPauseBeforeEdit": false
      },
      "sourceHints": {
        "possiblePaste": false,
        "suspiciousJump": false
      }
    }
  ]
}
